UKLawCaseScraper/CaseHeaderScraper.py
UKLawCaseScraper/CaseInfoScraper.py
UKLawCaseScraper/FullTextScraper.py
UKLawCaseScraper/Save_to_json.py
UKLawCaseScraper/__init__.py
tests/__init__.py
UKLawCaseScraper-0.4.3.dist-info/LICENSE
UKLawCaseScraper-0.4.3.dist-info/METADATA
UKLawCaseScraper-0.4.3.dist-info/WHEEL
UKLawCaseScraper-0.4.3.dist-info/top_level.txt
UKLawCaseScraper-0.4.3.dist-info/RECORD
