Metadata-Version: 2.1
Name: UKLawCaseScraper
Version: 0.4.3
Summary: A package for scrape case law informations.
Home-page: https://github.com/mrjoneidi/UKLawCaseScraper
Author: Mohammadreza Joneidi Jafari
Author-email: m.r.joneidi.02@gmail.com
Classifier: Programming Language :: Python :: 3
Classifier: Operating System :: OS Independent
Classifier: Framework :: Scrapy
Requires-Python: >=3.6
License-File: LICENSE
